pymongo-4.7.3.dist-info/WHEEL
pymongo-4.7.3.dist-info/top_level.txt
pymongo-4.7.3.dist-info/RECORD
pymongo-4.7.3.dist-info/METADATA
pymongo-4.7.3.dist-info/LICENSE
gridfs/__init__.py
gridfs/grid_file.py
gridfs/errors.py
gridfs/py.typed
pymongo/__init__.py
pymongo/results.py
pymongo/driver_info.py
pymongo/database.py
pymongo/bulk.py
pymongo/collation.py
pymongo/server_selectors.py
pymongo/response.py
pymongo/auth.py
pymongo/ocsp_cache.py
pymongo/logger.py
pymongo/operations.py
pymongo/client_options.py
pymongo/server_api.py
pymongo/command_cursor.py
pymongo/read_concern.py
pymongo/compression_support.py
pymongo/collection.py
pymongo/client_session.py
pymongo/mongo_client.py
pymongo/monitor.py
pymongo/pool.py
pymongo/event_loggers.py
pymongo/encryption.py
pymongo/hello.py
pymongo/_cmessagemodule.c
pymongo/message.py
pymongo/periodic_executor.py
pymongo/daemon.py
pymongo/aggregation.py
pymongo/monitoring.py
pymongo/typings.py
pymongo/server_description.py
pymongo/lock.py
pymongo/saslprep.py
pymongo/topology_description.py
pymongo/cursor.py
pymongo/socket_checker.py
pymongo/_version.py
pymongo/ssl_support.py
pymongo/ocsp_support.py
pymongo/max_staleness_selectors.py
pymongo/topology.py
pymongo/_csot.py
pymongo/_gcp_helpers.py
pymongo/server_type.py
pymongo/auth_oidc.py
pymongo/server.py
pymongo/ssl_context.py
pymongo/network.py
pymongo/_azure_helpers.py
pymongo/common.py
pymongo/helpers.py
pymongo/uri_parser.py
pymongo/_cmessage.cpython-37m-s390x-linux-gnu.so
pymongo/settings.py
pymongo/change_stream.py
pymongo/write_concern.py
pymongo/errors.py
pymongo/py.typed
pymongo/encryption_options.py
pymongo/auth_aws.py
pymongo/srv_resolver.py
pymongo/read_preferences.py
pymongo/pyopenssl_context.py
bson/__init__.py
bson/time64_limits.h
bson/binary.py
bson/_cbsonmodule.c
bson/time64_config.h
bson/objectid.py
bson/bson-endian.h
bson/_helpers.py
bson/son.py
bson/codec_options.py
bson/typings.py
bson/tz_util.py
bson/code.py
bson/min_key.py
bson/json_util.py
bson/_cbsonmodule.h
bson/buffer.c
bson/max_key.py
bson/buffer.h
bson/raw_bson.py
bson/dbref.py
