Metadata-Version: 2.1
Name: pymongo
Version: 4.7.3
Summary: Python driver for MongoDB <http://www.mongodb.org>
Author: The MongoDB Python Team
License:                                  Apache License
Project-URL: Homepage, https://www.mongodb.org
Project-URL: Documentation, https://pymongo.readthedocs.io
Project-URL: Source, https://github.com/mongodb/mongo-python-driver
Project-URL: Tracker, https://jira.mongodb.org/projects/PYTHON/issues
Keywords: bson,gridfs,mongo,mongodb,pymongo
Classifier: Development Status :: 5 - Production/Stable
Classifier: Intended Audience :: Developers
Classifier: License :: OSI Approved :: Apache Software License
Classifier: Operating System :: MacOS :: MacOS X
Classifier: Operating System :: Microsoft :: Windows
Classifier: Operating System :: POSIX
Classifier: Programming Language :: Python :: Implementation :: CPython
Classifier: Programming Language :: Python :: Implementation :: PyPy
Classifier: Programming Language :: Python :: 3
Classifier: Programming Language :: Python :: 3 :: Only
Classifier: Programming Language :: Python :: 3.7
Classifier: Programming Language :: Python :: 3.8
Classifier: Programming Language :: Python :: 3.9
Classifier: Programming Language :: Python :: 3.10
Classifier: Programming Language :: Python :: 3.11
Classifier: Programming Language :: Python :: 3.12
Classifier: Topic :: Database
Classifier: Typing :: Typed
Requires-Python: >=3.7
Provides-Extra: aws
Provides-Extra: encryption
Provides-Extra: gssapi
Provides-Extra: ocsp
Provides-Extra: snappy
Provides-Extra: srv
Provides-Extra: tls
Provides-Extra: zstd
Provides-Extra: test
License-File: LICENSE
